{
  "CheckoutSettings": {
    "GiftMessageEnabled": true,
    "PhoneNumber": "888-888-8888",
    "ContactEmail": "ericnation@test.com",
    "StoreName": "NGRX Store"
  },
  "ShippingAddress": {
    "PostCode": "85281",
    "Phone": "480-123-1232",
    "State": "Arizona",
    "City": "Tempe",
    "Street1": "1234 E Avenue St",
    "CompanyName": "Tristar",
    "LastName": "Smith",
    "FirstName": "Ryan "
  },
  "BillingAddress": {
    "Business": false,
    "PostCode": "",
    "Phone": "",
    "State": "",
    "City": "",
    "Street1": "",
    "CompanyName": "",
    "LastName": "",
    "FirstName": ""
  },
  "Cart": {
    "GuestEmail": "eric.nation@gmail.com",
    "GiftMessage": "Hello there! ",
    "ShippingAmount": 5,
    "ItemTotal": 53.54,
    "TaxAmount": 3.95,
    "QuantityPricingPercentDiscount": 0,
    "QuantityDiscountTax": 0,
    "QuantityDiscountAmount": 4.82,
    "DiscountTotal": 4.82,
    "DiscountTax": 0,
    "DiscountShipping": 0,
    "DiscountRetail": 4.82,
    "TotalDue": 57.67,
    "CartItemWeight": 1.173,
    "CanCheckout": true,
    "ItemCount": 3,
    "Discount": null,
    "GiftCertificates": []
  },
  "Items": [
    {
      "UnitPrice": 24.1,
      "CartRetailItemSizeId": 1003336,
      "CartRetailItemId": 1002840,
      "ProductStyleSizeId": 1004831,
      "ProductStyleId": 1000715,
      "Quantity": 2,
      "Size": "Medium",
      "Color": "Red Grey Slate",
      "ProductId": 1000026,
      "SidePreviews": [
        {
          "ProductOnlyUrl": "http://stores.inksoft.com/images/products/2758/products/07707/Sport_Scarlet_Red_Grey_Slate/front/500.png",
          "SideName": "Front"
        },
        {
          "ProductOnlyUrl": "http://stores.inksoft.com/images/products/2758/products/07707/Sport_Scarlet_Red_Grey_Slate/back/500.png",
          "SideName": "Back"
        }
      ],
      "QuantityDiscountAmount": 4.34,
      "PrintSetupCharge": 0,
      "PrintSetupCost": 0,
      "PriceScheduleId": 1000056,
      "Name": "Sport Scarlet TShirt"
    },
    {
      "UnitPrice": 5.34,
      "CartRetailItemSizeId": 1003337,
      "CartRetailItemId": 1002841,
      "ProductStyleSizeId": 1019638,
      "ProductStyleId": 1003109,
      "Quantity": 1,
      "Size": "Large",
      "Color": "White",
      "ProductId": 1000186,
      "SidePreviews": [
        {
          "ProductOnlyUrl": "http://stores.inksoft.com/images/products/2758/products/1080/White/front/500.png",
          "SideName": "Front"
        }
      ],
      "QuantityDiscountAmount": 0.48,
      "PrintSetupCharge": 1.3,
      "PrintSetupCost": 2,
      "Name": "Baby Rib Tank Top"
    }
  ],
  "PaymentInfo": {
    "CardNumber": "41111111111111111",
    "ExpirationMonth": "2",
    "ExpirationYear": "2019",
    "CvcCode": "123"
  },
  "ShippingMethod": {
    "Name": "FedEx Standard",
    "ProcessDays": 5,
    "Price": 4,
    "ID": 2
  },
  "ShippingMethods": [
    {
      "Name": "UPS",
      "ProcessDays": 3,
      "Price": 7.5,
      "ID": 1
    },
    {
      "Name": "FedEx Standard",
      "ProcessDays": 5,
      "Price": 4,
      "ID": 2
    },
    {
      "Name": "UPS Next Day Air",
      "ProcessDays": 1,
      "Price": 16.5,
      "ID": 3
    },
    {
      "Name": "USPS Priority Mail",
      "ProcessDays": 3,
      "Price": 8.55,
      "ID": 4
    }
  ]
}